[
  {
    "folder": "notion-api-initial-2026-02-09-14h41m39s-b8457cf",
    "branch": "notion-api-initial",
    "date": "2026-02-09",
    "time": "14:41:39",
    "commit": "b8457cf",
    "author": "unknown",
    "timestamp": 1771260019,
    "hasUnit": true,
    "hasIntegration": true,
    "hasCoverage": true,
    "unitPassed": 0,
    "unitTotal": 0,
    "integrationPassed": 0,
    "integrationTotal": 0,
    "coveragePercent": 0
  }
,
  {
    "folder": "notion-api-initial-2026-02-10-11h59m14s-4ed2d70",
    "branch": "notion-api-initial",
    "date": "2026-02-10",
    "time": "11:59:14",
    "commit": "4ed2d70",
    "author": "unknown",
    "timestamp": 1771260019,
    "hasUnit": true,
    "hasIntegration": true,
    "hasCoverage": true,
    "unitPassed": 0,
    "unitTotal": 0,
    "integrationPassed": 0,
    "integrationTotal": 0,
    "coveragePercent": 0
  }
,
  {
    "folder": "notion-api-initial-2026-02-10-12h17m35s-2e44ae8",
    "branch": "notion-api-initial",
    "date": "2026-02-10",
    "time": "12:17:35",
    "commit": "2e44ae8",
    "author": "unknown",
    "timestamp": 1771260019,
    "hasUnit": true,
    "hasIntegration": true,
    "hasCoverage": true,
    "unitPassed": 0,
    "unitTotal": 0,
    "integrationPassed": 0,
    "integrationTotal": 0,
    "coveragePercent": 0
  }
,
  {
    "folder": "notion-api-initial-2026-02-11-16h23m40s-877dec4",
    "branch": "notion-api-initial",
    "date": "2026-02-11",
    "time": "16:23:40",
    "commit": "877dec4",
    "author": "unknown",
    "timestamp": 1771260019,
    "hasUnit": true,
    "hasIntegration": true,
    "hasCoverage": true,
    "unitPassed": 0,
    "unitTotal": 0,
    "integrationPassed": 0,
    "integrationTotal": 0,
    "coveragePercent": 0
  }
,
  {
    "folder": "notion-api-initial-2026-02-16-15h29m51s-450dbcd",
    "branch": "notion-api-initial",
    "date": "2026-02-16",
    "time": "15:29:51",
    "commit": "450dbcd",
    "author": "unknown",
    "timestamp": 1771260019,
    "hasUnit": true,
    "hasIntegration": true,
    "hasCoverage": true,
    "unitPassed": 0,
    "unitTotal": 0,
    "integrationPassed": 0,
    "integrationTotal": 0,
    "coveragePercent": 0
  }
,
  {
    "folder": "notion-api-initial-2026-02-16-15h45m20s-d859b91",
    "branch": "notion-api-initial",
    "date": "2026-02-16",
    "time": "15:45:20",
    "commit": "d859b91",
    "author": "unknown",
    "timestamp": 1771260019,
    "hasUnit": true,
    "hasIntegration": true,
    "hasCoverage": true,
    "unitPassed": 0,
    "unitTotal": 0,
    "integrationPassed": 0,
    "integrationTotal": 0,
    "coveragePercent": 0
  }
,
  {
    "folder": "notion-api-initial-2026-02-16-16h40m18s-72aa013",
    "branch": "notion-api-initial",
    "date": "2026-02-16",
    "time": "16:40:18",
    "commit": "72aa013",
    "author": "unknown",
    "timestamp": 1771260019,
    "hasUnit": true,
    "hasIntegration": true,
    "hasCoverage": true,
    "unitPassed": 0,
    "unitTotal": 0,
    "integrationPassed": 0,
    "integrationTotal": 0,
    "coveragePercent": 0
  }

]
